<Locacao cpf="010.428.016-65">
  <nome>Vinicius Caio Enrico da Luz                                                                         </nome>
  <rg>36.310.070-2</rg>
  <nacionalidade>Brasileira                    </nacionalidade>
  <telefone>(84) 3824-9182                </telefone>
  <sexo>M                             </sexo>
  <nascimento>03/01/1991</nascimento>
</Locacao><Locacao cpf="110.994.805-07">
  <nome>Alexandre Renan Rocha                                                                               </nome>
  <rg>31.551.814-5</rg>
  <nacionalidade>Brasileira                    </nacionalidade>
  <telefone>(92) 3932-0284                </telefone>
  <sexo>M                             </sexo>
  <nascimento>03/01/1995</nascimento>
</Locacao><Locacao cpf="213.102.256-56">
  <nome>Renato Ryan Nascimento                                                                              </nome>
  <rg>42.501.689-4</rg>
  <nacionalidade>Brasileira                    </nacionalidade>
  <telefone>(11) 2860-8735                </telefone>
  <sexo>M                             </sexo>
  <nascimento>11/07/1989</nascimento>
</Locacao><Locacao cpf="293.482.312-19">
  <nome>José Caio Barbosa                                                                                   </nome>
  <rg>50.585.236-6</rg>
  <nacionalidade>Brasileira                    </nacionalidade>
  <telefone>(96) 2721-9132                </telefone>
  <sexo>M                             </sexo>
  <nascimento>17/08/1988</nascimento>
</Locacao><Locacao cpf="305.513.564-48">
  <nome>Thomas Caio Ian Fogaça                                                                              </nome>
  <rg>28.917.909-9</rg>
  <nacionalidade>Brasileira                    </nacionalidade>
  <telefone>(81) 3709-4275                </telefone>
  <sexo>M                             </sexo>
  <nascimento>26/04/1953</nascimento>
</Locacao><Locacao cpf="434.566.012-20">
  <nome>Milena Juliana Santos                                                                               </nome>
  <rg>47.647.321-4</rg>
  <nacionalidade>Brasileira                    </nacionalidade>
  <telefone>(96) 3875-4248                </telefone>
  <sexo>F                             </sexo>
  <nascimento>26/09/1962</nascimento>
</Locacao><Locacao cpf="442.006.520-64">
  <nome>Isabela Isabelly Ayla Costa                                                                         </nome>
  <rg>48.746.532-5</rg>
  <nacionalidade>Brasileira                    </nacionalidade>
  <telefone>(95) 2946-9632                </telefone>
  <sexo>F                             </sexo>
  <nascimento>03/04/1988</nascimento>
</Locacao><Locacao cpf="771.837.082-84">
  <nome>Lucas Jorge Souza                                                                                   </nome>
  <rg>26.079.729-7</rg>
  <nacionalidade>Brasileira                    </nacionalidade>
  <telefone>(82) 3714-4841                </telefone>
  <sexo>M                             </sexo>
  <nascimento>08/04/1997</nascimento>
</Locacao><Locacao cpf="794.425.833-28">
  <nome>Fábio Luan Peixoto                                                                                  </nome>
  <rg>11.149.389-4</rg>
  <nacionalidade>Brasileira                    </nacionalidade>
  <telefone>(98) 3997-9282                </telefone>
  <sexo>M                             </sexo>
  <nascimento>12/11/1995</nascimento>
</Locacao><Locacao cpf="800.205.859-34">
  <nome>Marcos Cauê Almada                                                                                  </nome>
  <rg>14.466.194-9</rg>
  <nacionalidade>Brasileira                    </nacionalidade>
  <telefone>(84) 2540-9362                </telefone>
  <sexo>M                             </sexo>
  <nascimento>26/08/1974</nascimento>
</Locacao><Locacao cpf="830.326.193-27">
  <nome>Cláudio Henrique Oliver Oliveira                                                                    </nome>
  <rg>28.530.352-1</rg>
  <nacionalidade>Brasileira                    </nacionalidade>
  <telefone>(11) 2678-5503                </telefone>
  <sexo>M                             </sexo>
  <nascimento>05/11/1968</nascimento>
</Locacao><Locacao cpf="901.793.448-46">
  <nome>Melissa Laís Ramos                                                                                  </nome>
  <rg>20.712.177-1</rg>
  <nacionalidade>Brasileira                    </nacionalidade>
  <telefone>(92) 3933-7643                </telefone>
  <sexo>F                             </sexo>
  <nascimento>06/07/1990</nascimento>
</Locacao><Locacao cpf="902.418.980-21">
  <nome>Matheus Yuri Silva                                                                                  </nome>
  <rg>21.373.999-9</rg>
  <nacionalidade>Brasileira                    </nacionalidade>
  <telefone>(95) 2661-6424                </telefone>
  <sexo>M                             </sexo>
  <nascimento>03/04/1981</nascimento>
</Locacao><Locacao cpf="947.487.728-91">
  <nome>Nina Patrícia Sales                                                                                 </nome>
  <rg>10.944.688-4</rg>
  <nacionalidade>Brasileira                    </nacionalidade>
  <telefone>(31) 3957-4998                </telefone>
  <sexo>F                             </sexo>
  <nascimento>11/08/1975</nascimento>
</Locacao>